submission_downloader/__init__.py
submission_downloader/__main__.py
submission_downloader-1.2.1.dist-info/LICENSE
submission_downloader-1.2.1.dist-info/METADATA
submission_downloader-1.2.1.dist-info/WHEEL
submission_downloader-1.2.1.dist-info/top_level.txt
submission_downloader-1.2.1.dist-info/RECORD
