Metadata-Version: 2.1
Name: submission-downloader
Version: 1.2.1
Summary: Downloads your submissions in bulk from the DMOJ website and any compatible forks.
Home-page: https://github.com/slightlyskepticalpotat/submission-downloader
Author: Anthony Chen
License: UNKNOWN
Platform: UNKNOWN
Classifier: Programming Language :: Python :: 3
Classifier: License :: OSI Approved :: GNU Affero General Public License v3
Classifier: Operating System :: OS Independent
Requires-Python: >=3.8
Requires-Dist: requests (>=2.22.0)
